ragloader/__init__.py
ragloader/exceptions.py
ragloader/orchestrator.py
ragloader/classification/__init__.py
ragloader/classification/classified_items.py
ragloader/classification/document_classifier.py
ragloader/conf/__init__.py
ragloader/conf/config.py
ragloader/conf/config.toml
ragloader/db/__init__.py
ragloader/db/qdrant_connector.py
ragloader/embedding/__init__.py
ragloader/embedding/mapper.py
ragloader/embedding/common/chunk_embedder.py
ragloader/embedding/common/document_embedder.py
ragloader/embedding/common/embedded_items.py
ragloader/embedding/embedders/all_mpnet_base.py
ragloader/embedding/embedders/huggingface_embedder.py
ragloader/embedding/embedders/legal_bert.py
ragloader/embedding/embedders/openai_ada.py
ragloader/embedding/embedders/orlikb_kartonbert_use.py
ragloader/embedding/embedders/paraphrase_multilingual_mpnet.py
ragloader/extraction/__init__.py
ragloader/extraction/document_extractor.py
ragloader/extraction/extracted_items.py
ragloader/indexing/__init__.py
ragloader/indexing/documents.py
ragloader/indexing/indexer.py
ragloader/parsing/__init__.py
ragloader/parsing/mapper.py
ragloader/parsing/common/__init__.py
ragloader/parsing/common/document_parser.py
ragloader/parsing/common/file_parser.py
ragloader/parsing/common/parsed_items.py
ragloader/parsing/docx_parsers/__init__.py
ragloader/parsing/docx_parsers/docx2txt_parser.py
ragloader/parsing/image_parsers/__init__.py
ragloader/parsing/image_parsers/openai_image_parser.py
ragloader/parsing/pdf_parsers/__init__.py
ragloader/parsing/pdf_parsers/pymupdf_parser.py
ragloader/parsing/txt_parsers/__init__.py
ragloader/parsing/txt_parsers/txt_parser.py
ragloader/splitting/__init__.py
ragloader/splitting/mapper.py
ragloader/splitting/common/__init__.py
ragloader/splitting/common/chunked_items.py
ragloader/splitting/common/document_splitter.py
ragloader/splitting/common/text_splitter.py
ragloader/splitting/text_splitters/__init__.py
ragloader/splitting/text_splitters/base_text_splitters.py
ragloader-0.1.13.dist-info/METADATA
ragloader-0.1.13.dist-info/WHEEL
ragloader-0.1.13.dist-info/RECORD
